spydrnet/VERSION
spydrnet/__init__.py
spydrnet/clone.py
spydrnet/flatten.py
spydrnet/release.py
spydrnet/uniquify.py
spydrnet/callback/__init__.py
spydrnet/callback/callback_listener.py
spydrnet/compare/__init__.py
spydrnet/compare/compare_netlists.py
spydrnet/composers/__init__.py
spydrnet/composers/eblif/__init__.py
spydrnet/composers/eblif/eblif_composer.py
spydrnet/composers/edif/__init__.py
spydrnet/composers/edif/composer.py
spydrnet/composers/edif/edifify_names.py
spydrnet/composers/verilog/__init__.py
spydrnet/composers/verilog/composer.py
spydrnet/global_state/__init__.py
spydrnet/global_state/global_callback.py
spydrnet/global_state/global_service.py
spydrnet/ir/__init__.py
spydrnet/ir/bundle.py
spydrnet/ir/cable.py
spydrnet/ir/definition.py
spydrnet/ir/element.py
spydrnet/ir/first_class_element.py
spydrnet/ir/innerpin.py
spydrnet/ir/instance.py
spydrnet/ir/library.py
spydrnet/ir/netlist.py
spydrnet/ir/outerpin.py
spydrnet/ir/pin.py
spydrnet/ir/port.py
spydrnet/ir/wire.py
spydrnet/ir/views/__init__.py
spydrnet/ir/views/dictview.py
spydrnet/ir/views/listview.py
spydrnet/ir/views/outerpinsview.py
spydrnet/ir/views/setview.py
spydrnet/parsers/__init__.py
spydrnet/parsers/primitive_library_reader.py
spydrnet/parsers/eblif/__init__.py
spydrnet/parsers/eblif/eblif_parser.py
spydrnet/parsers/eblif/eblif_tokenizer.py
spydrnet/parsers/eblif/eblif_tokens.py
spydrnet/parsers/edif/__init__.py
spydrnet/parsers/edif/edif_tokens.py
spydrnet/parsers/edif/parser.py
spydrnet/parsers/edif/tokenizer.py
spydrnet/parsers/primatives/__init__.py
spydrnet/parsers/primatives/parse_primatives.py
spydrnet/parsers/primatives/parsetab.py
spydrnet/parsers/verilog/__init__.py
spydrnet/parsers/verilog/parser.py
spydrnet/parsers/verilog/tokenizer.py
spydrnet/parsers/verilog/verilog_token_factory.py
spydrnet/parsers/verilog/verilog_tokens.py
spydrnet/plugins/__init__.py
spydrnet/plugins/namespace_manager/__init__.py
spydrnet/plugins/namespace_manager/default_namespace.py
spydrnet-1.13.0.dist-info/LICENSE
spydrnet-1.13.0.dist-info/METADATA
spydrnet-1.13.0.dist-info/WHEEL
spydrnet-1.13.0.dist-info/top_level.txt
spydrnet-1.13.0.dist-info/RECORD
