Metadata-Version: 2.1
Name: spydrnet
Version: 1.13.0
Summary: Python package for analyzing and transforming netlists
Home-page: https://byuccl.github.io/spydrnet
Author: Andrew Keller
Author-email: andrewmkeller@byu.edu
Maintainer: SpyDrNet Developers
Maintainer-email: spydrnet-discuss@googlegroups.com
License: BSD
Project-URL: Bug Tracker, https://github.com/byuccl/spydrnet/issues
Project-URL: Documentation, https://byuccl.github.io/spydrnet/docs/stable
Project-URL: Source Code, https://github.com/byuccl/spydrnet
Keywords: Netlist,Analysis,Transformation,netlist,FPGA,primitives,module,port,EDIF,Digital,Hardware
Platform: Linux
Platform: Mac OSX
Platform: Windows
Platform: Unix
Classifier: Development Status :: 5 - Production/Stable
Classifier: Intended Audience :: Developers
Classifier: Intended Audience :: Education
Classifier: Intended Audience :: Science/Research
Classifier: License :: OSI Approved :: BSD License
Classifier: Operating System :: OS Independent
Classifier: Programming Language :: Python :: 3
Classifier: Programming Language :: Python :: 3.6
Classifier: Programming Language :: Python :: 3.7
Classifier: Programming Language :: Python :: 3.8
Classifier: Programming Language :: Python :: 3.9
Classifier: Programming Language :: Python :: 3.10
Classifier: Programming Language :: Python :: 3 :: Only
Classifier: Topic :: Education
Classifier: Topic :: Scientific/Engineering
Classifier: Topic :: Scientific/Engineering :: Information Analysis
Classifier: Topic :: Scientific/Engineering :: Electronic Design Automation (EDA)
Classifier: Topic :: Software Development :: Libraries :: Python Modules
Requires-Python: >=3.6
License-File: LICENSE
Provides-Extra: all
Requires-Dist: pytest ; extra == 'all'
Requires-Dist: ply ; extra == 'all'
Provides-Extra: ply
Requires-Dist: ply ; extra == 'ply'
Provides-Extra: pytest
Requires-Dist: pytest ; extra == 'pytest'
